armmwave
