Metadata-Version: 2.1
Name: armmwave
Version: 0.0a2
Summary: Calculate mm-wave transmittance and reflectance of materials
Home-page: https://github.com/anadolski/armmwave
Author: Andrew Nadolski
Author-email: andrew.nadolski@gmail.com
License: MIT
Platform: Linux
Platform: MacOS X
Classifier: Programming Language :: Python :: 3
Classifier: License :: OSI Approved :: MIT License
Classifier: Operating System :: MacOS :: MacOS X
Classifier: Operating System :: POSIX :: Linux
Classifier: Development Status :: 3 - Alpha
Requires-Python: >=3.5
